{
  "type": "Feature",
  "properties": {
    "addr:full":"Recorded Information, Waddesdon Aylesbury Buckinghamshire HP18 0JH",
    "addr:housenumber":"waddesdon",
    "addr:postcode":"hp18 0jh",
    "addr:street":"Aylesbury",
    "iso:country":"GB",
    "sg:address":"Recorded Information, Waddesdon",
    "sg:city":"Aylesbury",
    "sg:classifiers":[
        {
            "category":"Landmark",
            "subcategory":"Tourist Attraction",
            "type":"Public Place"
        }
    ],
    "sg:phone":"+44 1296 653203",
    "sg:postcode":"HP18 0JH",
    "sg:province":"Buckinghamshire",
    "sg:tags":[
        "interest"
    ],
    "wof:name":"Waddesdon Manor National Trust",
    "wof:placetype":"venue"
},
  "geometry": {"coordinates":[-0.919449,51.846096],"type":"Point"}
}
